cdk_personalize_datasetgroup/__init__.py
cdk_personalize_datasetgroup/py.typed
cdk_personalize_datasetgroup/_jsii/__init__.py
cdk_personalize_datasetgroup/_jsii/cdk-personalize-datasetgroup@1.73.1.jsii.tgz
cdk_personalize_datasetgroup-1.73.1.dist-info/METADATA
cdk_personalize_datasetgroup-1.73.1.dist-info/WHEEL
cdk_personalize_datasetgroup-1.73.1.dist-info/top_level.txt
cdk_personalize_datasetgroup-1.73.1.dist-info/RECORD
